datadoc_editor/__init__.py
datadoc_editor/app.py
datadoc_editor/config.py
datadoc_editor/constants.py
datadoc_editor/enums.py
datadoc_editor/py.typed
datadoc_editor/state.py
datadoc_editor/utils.py
datadoc_editor/wsgi.py
datadoc_editor/assets/app_style.css
datadoc_editor/assets/bootstrap-icons.css
datadoc_editor/assets/bootstrap.min.css
datadoc_editor/assets/controlbar_style.css
datadoc_editor/assets/dropdown_style.css
datadoc_editor/assets/favicon.ico
datadoc_editor/assets/global_variables_style.css
datadoc_editor/assets/header.css
datadoc_editor/assets/html-language-script.js
datadoc_editor/assets/input_style.css
datadoc_editor/assets/multidropdown_style.css
datadoc_editor/assets/multilanguage_style.css
datadoc_editor/assets/workspace_style.css
datadoc_editor/assets/workspace_tab.css
datadoc_editor/assets/fonts/bootstrap-icons.woff
datadoc_editor/assets/fonts/bootstrap-icons.woff2
datadoc_editor/frontend/__init__.py
datadoc_editor/frontend/constants.py
datadoc_editor/frontend/callbacks/__init__.py
datadoc_editor/frontend/callbacks/dataset.py
datadoc_editor/frontend/callbacks/dataset_callbacks.py
datadoc_editor/frontend/callbacks/global_variables.py
datadoc_editor/frontend/callbacks/global_variables_callbacks.py
datadoc_editor/frontend/callbacks/pseudonymization_callbacks.py
datadoc_editor/frontend/callbacks/register_callbacks.py
datadoc_editor/frontend/callbacks/use_restrictions_callbacks.py
datadoc_editor/frontend/callbacks/utils.py
datadoc_editor/frontend/callbacks/variables.py
datadoc_editor/frontend/callbacks/variables_callbacks.py
datadoc_editor/frontend/components/__init__.py
datadoc_editor/frontend/components/builders.py
datadoc_editor/frontend/components/control_bars.py
datadoc_editor/frontend/components/global_variables_builders.py
datadoc_editor/frontend/components/identifiers.py
datadoc_editor/frontend/fields/__init__.py
datadoc_editor/frontend/fields/display_base.py
datadoc_editor/frontend/fields/display_dataset.py
ssb_datadoc-1.5.1.dist-info/METADATA
ssb_datadoc-1.5.1.dist-info/WHEEL
ssb_datadoc-1.5.1.dist-info/entry_points.txt
ssb_datadoc-1.5.1.dist-info/licenses/LICENSE
ssb_datadoc-1.5.1.dist-info/RECORD
