Metadata-Version: 2.4
Name: ssb-datadoc
Version: 1.5.1
Summary: Document dataset metadata. For use in Statistics Norway's metadata system.
Project-URL: homepage, https://github.com/statisticsnorway/datadoc-editor
Project-URL: repository, https://github.com/statisticsnorway/datadoc-editor
Project-URL: documentation, https://statisticsnorway.github.io/datadoc-editor
Project-URL: changelog, https://github.com/statisticsnorway/datadoc-editor/releases
Author-email: Statistics Norway <metadata@ssb.no>
License-Expression: MIT
License-File: LICENSE
Classifier: Development Status :: 4 - Beta
Classifier: Framework :: Dash
Classifier: Typing :: Typed
Requires-Python: >=3.12
Requires-Dist: arrow>=1.3.0
Requires-Dist: dapla-toolbelt-metadata>=0.12.1
Requires-Dist: dash-bootstrap-components>=1.1.0
Requires-Dist: dash>=2.15.0
Requires-Dist: flask-healthz>=0.0.3
Requires-Dist: gunicorn>=23.0.0
Requires-Dist: pydantic>=2.5.2
Requires-Dist: python-dotenv>=1.0.1
Requires-Dist: ssb-dash-components>=0.11.1
